headless_wheel_builder/__init__.py
headless_wheel_builder/__main__.py
headless_wheel_builder/exceptions.py
headless_wheel_builder/actions/__init__.py
headless_wheel_builder/actions/cli.py
headless_wheel_builder/actions/generator.py
headless_wheel_builder/actions/templates.py
headless_wheel_builder/cache/__init__.py
headless_wheel_builder/cache/cli.py
headless_wheel_builder/cache/models.py
headless_wheel_builder/cache/registry.py
headless_wheel_builder/cache/storage.py
headless_wheel_builder/changelog/__init__.py
headless_wheel_builder/changelog/cli.py
headless_wheel_builder/changelog/generator.py
headless_wheel_builder/changelog/parser.py
headless_wheel_builder/cli/__init__.py
headless_wheel_builder/cli/main.py
headless_wheel_builder/core/__init__.py
headless_wheel_builder/core/analyzer.py
headless_wheel_builder/core/builder.py
headless_wheel_builder/core/source.py
headless_wheel_builder/depgraph/__init__.py
headless_wheel_builder/depgraph/analyzer.py
headless_wheel_builder/depgraph/cli.py
headless_wheel_builder/depgraph/models.py
headless_wheel_builder/depgraph/resolver.py
headless_wheel_builder/github/__init__.py
headless_wheel_builder/github/cli.py
headless_wheel_builder/github/client.py
headless_wheel_builder/github/models.py
headless_wheel_builder/isolation/__init__.py
headless_wheel_builder/isolation/base.py
headless_wheel_builder/isolation/docker.py
headless_wheel_builder/isolation/venv.py
headless_wheel_builder/metrics/__init__.py
headless_wheel_builder/metrics/cli.py
headless_wheel_builder/metrics/collector.py
headless_wheel_builder/metrics/models.py
headless_wheel_builder/metrics/storage.py
headless_wheel_builder/multirepo/__init__.py
headless_wheel_builder/multirepo/cli.py
headless_wheel_builder/multirepo/config.py
headless_wheel_builder/multirepo/manager.py
headless_wheel_builder/notify/__init__.py
headless_wheel_builder/notify/cli.py
headless_wheel_builder/notify/models.py
headless_wheel_builder/notify/providers.py
headless_wheel_builder-0.3.0.dist-info/METADATA
headless_wheel_builder-0.3.0.dist-info/WHEEL
headless_wheel_builder-0.3.0.dist-info/entry_points.txt
headless_wheel_builder-0.3.0.dist-info/licenses/LICENSE
headless_wheel_builder-0.3.0.dist-info/RECORD
